sensact/__init__.py
sensact-0.0.0.dist-info/licenses/LICENSE
sensact-0.0.0.dist-info/METADATA
sensact-0.0.0.dist-info/WHEEL
sensact-0.0.0.dist-info/top_level.txt
sensact-0.0.0.dist-info/RECORD
