Metadata-Version: 2.4
Name: sensact
Version: 0.0.0
Summary: A Python package
Project-URL: Homepage, https://github.com/yourusername/sensact
Classifier: Programming Language :: Python :: 3
Classifier: License :: OSI Approved :: Apache Software License
Classifier: Operating System :: OS Independent
Requires-Python: >=3.8
License-File: LICENSE
Dynamic: license-file
